etc/sudoers.d/stoqserver
etc/supervisor/conf.d/stoqserver.conf
stoqserver/__init__.py
stoqserver/__installed__.py
stoqserver/__main__.py
stoqserver/client.py
stoqserver/common.py
stoqserver/main.py
stoqserver/server.py
stoqserver/taskmanager.py
stoqserver/tasks.py
stoqserver/lib/__init__.py
stoqserver/lib/duplicatibackup.py
stoqserver/lib/duplicitybackup.py
stoqserver/lib/restful.py
stoqserver/lib/stacktracer.py
stoqserver/lib/xmlrpcresource.py
stoqserver/lib/test/__init__.py
stoqserver/lib/test/test_restful.py
stoqserver-0.26.1.data/data/share/locale/pt_BR/LC_MESSAGES/stoqserver.mo
stoqserver-0.26.1.data/data/share/stoqserver/htsql/config.yml
stoqserver-0.26.1.data/data/share/stoqserver/scripts/duplicitybackup.py
stoqserver-0.26.1.data/data/share/stoqserver/webrtc/buffer-split.js
stoqserver-0.26.1.data/data/share/stoqserver/webrtc/package.json
stoqserver-0.26.1.data/data/share/stoqserver/webrtc/rtc.js
stoqserver-0.26.1.data/data/share/stoqserver/webrtc/snapshooter.js
stoqserver-0.26.1.data/data/share/stoqserver/webrtc/start.sh
stoqserver-0.26.1.data/scripts/stoqserver
stoqserver-0.26.1.dist-info/DESCRIPTION.rst
stoqserver-0.26.1.dist-info/METADATA
stoqserver-0.26.1.dist-info/RECORD
stoqserver-0.26.1.dist-info/WHEEL
stoqserver-0.26.1.dist-info/metadata.json
stoqserver-0.26.1.dist-info/top_level.txt
stoqserver-0.26.1.dist-info/zip-safe
