Metadata-Version: 2.0
Name: stoqserver
Version: 0.26.1
Summary: Stoq server
Home-page: http://www.stoq.com.br
Author: Stoq Team
Author-email: stoq-devel@async.com.br
License: GNU LGPL 2.1 (see COPYING)
Platform: UNKNOWN
Requires-Dist: Twisted (>=10.0.0)
Requires-Dist: flask (>=0.10.1)
Requires-Dist: flask-restful (>=0.3.4)
Requires-Dist: requests (>=2.2)
Requires-Dist: netifaces
Requires-Dist: gevent (>=1.1.0)
